[
    {
      "name": "Home",
      "prix": "3.99€/mois",
      "rating": 3.5,
      "package": {
        "capteurs": 1,
        "station": 0,
        "pass": "Classic"
      },
      "description": "Le meilleur pour découvrir nos services et l'application directement chez vous.",
      "image": "https://raw.githubusercontent.com/Gabriel-Jagueneau/weatherPod/refs/heads/main/storage/images/icons/station-meteo.png"
    },
    {
      "name": "Outdoor",
      "prix": "10.99€/mois",
      "rating": 4.8,
      "package": {
        "capteurs": 4,
        "station": 0,
        "pass": "Classic"
      },
      "description": "Idéal pour les petits jardins et potagers amateurs."
    },
    {
      "name": "Station",
      "prix": "27.99€/mois",
      "rating": 2.8,
      "package": {
        "capteurs": 8,
        "station": 1,
        "pass": "Pro"
      },
      "description": "Idéal pour les grand jardins et les potagers professionels."
    }
]